<form name="TCC">
	<page number="1">
		<field>
        <dc-schema>dc</dc-schema>
        <dc-element>contributor</dc-element>
        <dc-qualifier>author</dc-qualifier>
        <repeatable>true</repeatable>
        <label>Autor(es)*</label>
        <input-type>name</input-type>
        <hint>Digite o nome do autor(es) do Trabalho de Conclusão de Curso</hint>
        <required>Digite pelo menos o nome de um autor</required>
    	</field>

    	<field>
        <dc-schema>dc</dc-schema>
        <dc-element>contributor</dc-element>
        <dc-qualifier>advisor</dc-qualifier>
        <repeatable>true</repeatable>
        <label>Orientador(es)*</label>
        <input-type>name</input-type>
        <hint>Digite o nome do orientador(es) do Trabalho de Conclusão de Curso.</hint>
        <required>Digite pelo menos o nome de um orientador.</required>
    	</field>

    	<field>
        <dc-schema>dc</dc-schema>
        <dc-element>contributor</dc-element>
        <dc-qualifier>coadvisor</dc-qualifier>
        <repeatable>true</repeatable>
        <label>Coorientador(es)</label>
        <input-type>name</input-type>
        <hint>Digite o nome do coorientador(es) do Trabalho de Conclusão de Curso.</hint>
        <required></required>
    	</field>

    	<field>
        <dc-schema>dc</dc-schema>
        <dc-element>title</dc-element>
        <dc-qualifier></dc-qualifier>
        <repeatable>false</repeatable>
        <label>Tïtulo*</label>
        <input-type>onebox</input-type>
        <hint>Digite o nome do tïtulo do Trabalho de Conclusão de Curso.</hint>
        <required>Digite o tïtulo do TCC.</required>
    	</field>

		<field>
        <dc-schema>dc</dc-schema>
        <dc-element>type</dc-element>
        <dc-qualifier></dc-qualifier>
        <repeatable>false</repeatable>
        <label>Tipo*</label>
        <input-type value-pairs-name="typ4">dropdown</input-type>
        <hint>Selecione o tipo do domumento.</hint>
        <required>Selecione o tipo do domumento.</required>
    	</field>

    	<field>
        <dc-schema>dc</dc-schema>
        <dc-element>description</dc-element>
        <dc-qualifier>abstract</dc-qualifier>
        <repeatable>false</repeatable>
        <label>Resumo*</label>
        <input-type>onebox</input-type>
        <hint>Digite o resumo (em português) do Trabalho de Conclusão de Curso.</hint>
        <required>Digite resumo do TCC.</required>
    	</field>

    	<field>
        <dc-schema>dc</dc-schema>
        <dc-element>description</dc-element>
        <dc-qualifier>abstract</dc-qualifier>
        <repeatable>false</repeatable>
        <label>Resumo (Outro idioma)</label>
        <input-type>onebox</input-type>
        <hint>Digite o resumo (abstract) do Trabalho de Conclusão de Curso em outro idioma.</hint>
        <required></required>
    	</field>
        
        <field>
        <dc-schema>dc</dc-schema>
        <dc-element>language</dc-element>
        <dc-qualifier>iso</dc-qualifier>
        <repeatable>false</repeatable>
        <label>Idioma*</label>
        <input-type>onebox</input-type>
        <hint>Digite o idioma que predomina no Trabalho de Conclusão de Curso.</hint>
        <required>Digite o idioma.</required>
        </field>

        <field>
        <dc-schema>dc</dc-schema>
        <dc-element>subject</dc-element>
        <dc-qualifier></dc-qualifier>
        <repeatable>true</repeatable>
        <label>Palavra-chave</label>
        <input-type>onebox</input-type>
        <hint>Digite as palavras-chave do Trabalho de Conclusão de Curso, uma a uma.</hint>
        <required></required>
        </field>

        <field>
        <dc-schema>dc</dc-schema>
        <dc-element>date</dc-element>
        <dc-qualifier>issued</dc-qualifier>
        <repeatable>false</repeatable>
        <label>Data de publicaçã</label>
        <input-type>date</input-type>
        <hint>Digite a data em que o Trabalho de Conclusão de Curso foi publicado.</hint>
        <required></required>
        </field>

        <field>
        <dc-schema>dc</dc-schema>
        <dc-element>degree</dc-element>
        <dc-qualifier>grantor</dc-qualifier>
        <repeatable>false</repeatable>
        <label>Instituição*</label>
        <input-type>onebox</input-type>
        <hint>Digite o nome da instituição a qual o Trabalho de Conclusão de Curso e vinculado.</hint>
        <required>Digite o nome da instituição.</required>
        </field>

        <field>
        <dc-schema>dc</dc-schema>
        <dc-element>degree</dc-element>
        <dc-qualifier>department</dc-qualifier>
        <repeatable>false</repeatable>
        <label>Departamento*</label>
        <input-type>onebox</input-type>
        <hint>Digite o nome do departamento em que o Trabalho de Conclusão de Curso foi desenvolvido.</hint>
        <required>Digite o nome do departamento.</required>
        </field>
        
        <field>
        <dc-schema>dc</dc-schema>
        <dc-element>degree</dc-element>
        <dc-qualifier>local</dc-qualifier>
        <repeatable>false</repeatable>
        <label>Local*</label>
        <input-type>onebox</input-type>
        <hint>Digite o nome do local em que o Trabalho de Conclusão de Curso foi defendido.</hint>
        <required>Digite o local.</required>
        </field>    

        <field>
        <dc-schema>dc</dc-schema>
        <dc-element>date</dc-element>
        <dc-qualifier></dc-qualifier>
        <repeatable>false</repeatable>
        <label>Data de defesa</label>
        <input-type>date</input-type>
        <hint>Digite a data em que o Trabalho de Conclusão de Curso foi defendido.</hint>
        <required></required>
        </field>     
        
        <field>
        <dc-schema>dc</dc-schema>
        <dc-element>degree</dc-element>
        <dc-qualifier>graduation</dc-qualifier>
        <repeatable>false</repeatable>
        <label>Curso*</label>
        <input-type>onebox</input-type>
        <hint>Digite o nome do curso o qual Trabalho de Conclusão de Curso esta vinculado.</hint>
        <required>Digite o curso.</required>
        </field> 

        <field>
        <dc-schema>dc</dc-schema>
        <dc-element>degree</dc-element>
        <dc-qualifier>level</dc-qualifier>
        <repeatable>false</repeatable>
        <label>Nïïïvel*</label>
        <input-type value-pairs-name="typ5">dropdown</input-type>
        <hint>Selecione o nïvel.</hint>
        <required>Digite o nïvel.</required>
        </field> 
	</page>
</form>